{"cameraMode":{"drawMode":0,"name":"Shaded","section":"Shading Mode"},"sceneLighting":true,"audioPlay":false,"sceneViewState":{"m_AlwaysRefresh":false,"showFog":true,"showSkybox":true,"showFlares":true,"showImageEffects":true,"showParticleSystems":true,"showVisualEffectGraphs":true,"m_FxEnabled":true},"in2DMode":false,"pivot":{"x":0.0,"y":-3.17332124710083,"z":0.0},"rotation":{"x":0.19190599024295808,"y":0.47018083930015566,"z":-0.10553610324859619,"w":0.8549702167510986},"size":3.055271625518799,"orthographic":false}